[{"Job title": "Product Manager, Payments & Fraud", "Company name": "Lime", "City": "", "State": "Remote", "Posting date": "02.10.2021"}, {"Job title": "Senior Payments Analyst", "Company name": "Remote Technology, Inc.", "City": "", "State": "Remote", "Posting date": "13.10.2021"}, {"Job title": "Customer Support Representative - Payments", "Company name": "Zeal", "City": "Los Angeles", "State": "CA", "Posting date": "22.09.2021"}, {"Job title": "Program Manager, Payments", "Company name": "Amazon.com Services LLC", "City": "Seattle", "State": "WA", "Posting date": "05.10.2021"}, {"Job title": "Global Head of Payments Compliance Controls", "Company name": "Amazon.com Services LLC", "City": "Arlington", "State": "VA", "Posting date": ">18.09.2021"}, {"Job title": "Manager, Consumer Payments Optimization", "Company name": "The Walt Disney Company (Corporate)", "City": "Burbank", "State": "CA", "Posting date": "05.10.2021"}, {"Job title": "VP, Product - Payments (Remote)", "Company name": "Guild Education", "City": "Denver", "State": "CO, Remote", "Posting date": "09.10.2021"}, {"Job title": "Director of Product, Payments [US REMOTE ROLE]", "Company name": "GameStop", "City": "Grapevine", "State": "TX, Remote", "Posting date": "15.10.2021"}, {"Job title": "Work From Home Senior Customer Service Expert - eBay Payments Agent", "Company name": "eBay Inc.", "City": "Draper", "State": "UT, Remote", "Posting date": "14.10.2021"}, {"Job title": "Backend Engineer, Payments", "Company name": "Panasonic Corporation of North America", "City": "Palo Alto", "State": "CA", "Posting date": "18.09.2021"}, {"Job title": "Engineering Manager - Payments", "Company name": "Twitch Interactive, Inc.", "City": "Seattle", "State": "WA", "Posting date": "15.10.2021"}, {"Job title": "PAYMENTS & FRAUD ANALYST", "Company name": "Hard Rock International (USA), Inc.", "City": "Hollywood", "State": "FL", "Posting date": ">18.09.2021"}, {"Job title": "Customer Support Representative - Payments", "Company name": "Zeal", "City": "San Francisco", "State": "CA, Remote", "Posting date": "22.09.2021"}, {"Job title": "Director of Payments", "Company name": "Velocity Global", "City": "", "State": "Remote", "Posting date": "09.10.2021"}, {"Job title": "Payments Associate", "Company name": "PRA Health Sciences", "City": "", "State": "Remote", "Posting date": "01.10.2021"}, {"Job title": "Finance Manager, Digital & Emerging Payments", "Company name": "Amazon.com Services LLC", "City": "Seattle", "State": "WA", "Posting date": ">18.09.2021"}, {"Job title": "Head of Digital Payments Transformation", "Company name": "Bank of America", "City": "Charlotte", "State": "NC", "Posting date": "06.10.2021"}, {"Job title": "Payments Monitoring Manager", "Company name": "CURO Financial Technologies Corporation", "City": "", "State": "Wisconsin, Remote", "Posting date": "16.10.2021"}, {"Job title": "Partnerships Manager, Payments", "Company name": "Etsy", "City": "Brooklyn", "State": "NY, Remote", "Posting date": "06.10.2021"}, {"Job title": "Product Manager, Payments", "Company name": "Mercari", "City": "", "State": "California, Remote", "Posting date": ">18.09.2021"}, {"Job title": "Solution Delivery Analyst \u2013 Payments Research, GCI Analytics", "Company name": "McKinsey & Company", "City": "Atlanta", "State": "GA", "Posting date": "15.10.2021"}, {"Job title": "Payments Operations Associate Director", "Company name": "MarginEdge", "City": "Fairfax", "State": "VA", "Posting date": "02.10.2021"}, {"Job title": "Engineering Manager, Payments Platform", "Company name": "Etsy", "City": "Brooklyn", "State": "NY, Remote", "Posting date": "07.10.2021"}, {"Job title": "Compliance Operations for Finance and Payments", "Company name": "TikTok", "City": "Los Angeles", "State": "CA, Remote", "Posting date": "15.10.2021"}, {"Job title": "Senior Manager \u2013 Enterprise Payments", "Company name": "T-Mobile", "City": "Bellevue", "State": "WA", "Posting date": ">18.09.2021"}, {"Job title": "Senior Manager, Consumer Payments", "Company name": "The Walt Disney Company (Corporate)", "City": "Burbank", "State": "CA", "Posting date": "05.10.2021"}, {"Job title": "Sr. Product Manager, Advertising Billing & Payments", "Company name": "Disney Media & Entertainment Distribution", "City": "New York", "State": "NY", "Posting date": "17.10.2021"}, {"Job title": "Payments Program Manager", "Company name": "Amazon.com Services LLC", "City": "Seattle", "State": "WA", "Posting date": ">18.09.2021"}, {"Job title": "Payments Analyst", "Company name": "Silvergate", "City": "", "State": "Remote", "Posting date": ">18.09.2021"}, {"Job title": "Director of Product, Payments [US REMOTE ROLE]", "Company name": "GameStop", "City": "Boston", "State": "MA, Remote", "Posting date": "15.10.2021"}, {"Job title": "Payments Monitoring Manager", "Company name": "CURO Financial Technologies Corporation", "City": "", "State": "Kansas, Remote", "Posting date": "12.10.2021"}, {"Job title": "Payments and Loyalty Strategy Manager", "Company name": "ExxonMobil", "City": "Spring", "State": "TX", "Posting date": "16.10.2021"}, {"Job title": "Customer Support Representative - Payments", "Company name": "Zeal", "City": "Palo Alto", "State": "CA", "Posting date": "22.09.2021"}, {"Job title": "Senior Audit Manager - Deposits and Payments (100% Remote Work Opportunity)", "Company name": "USAA", "City": "San Antonio", "State": "TX, Remote", "Posting date": "02.10.2021"}, {"Job title": "Head of Payments", "Company name": "CrowdRise", "City": "Redwood City", "State": "CA, Temporarily Remote", "Posting date": "06.10.2021"}, {"Job title": "Product Prophet- Payments", "Company name": "Shazam.net", "City": "", "State": "Remote", "Posting date": "29.09.2021"}, {"Job title": "Customer Support Representative - Payments", "Company name": "Zeal", "City": "San Jose", "State": "CA, Remote", "Posting date": "15.10.2021"}, {"Job title": "Customer Support Representative - Payments", "Company name": "Zeal", "City": "Sacramento", "State": "CA", "Posting date": "22.09.2021"}, {"Job title": "Director of Payments", "Company name": "Remote Technology, Inc.", "City": "", "State": "Remote", "Posting date": "15.10.2021"}, {"Job title": "Payments Acceptance Manager", "Company name": "Uber", "City": "San Francisco", "State": "CA", "Posting date": ">18.09.2021"}, {"Job title": "Senior Director of Product Management, Marketplace Payments", "Company name": "Etsy", "City": "Brooklyn", "State": "NY, Remote", "Posting date": "07.10.2021"}, {"Job title": "Product Manager, Payments Integration", "Company name": "Sage", "City": "Atlanta", "State": "GA", "Posting date": "24.09.2021"}, {"Job title": "Head of Payments", "Company name": "CrowdRise", "City": "", "State": "Remote", "Posting date": ">18.09.2021"}, {"Job title": "Product Manager, Payments", "Company name": "Constrafor", "City": "", "State": "New York State, Remote", "Posting date": "26.09.2021"}, {"Job title": "Customer Support Representative - Payments", "Company name": "Zeal", "City": "San Diego", "State": "CA", "Posting date": "22.09.2021"}, {"Job title": "Work From Home Senior Customer Service Expert - eBay Payments Agent", "Company name": "eBay Inc.", "City": "583 W Ebay Way", "State": "Dr, Remote", "Posting date": "14.10.2021"}, {"Job title": "Payments Monitoring Manager", "Company name": "CURO Financial Technologies Corporation", "City": "", "State": "Illinois, Remote", "Posting date": "12.10.2021"}, {"Job title": "Customer Support Representative - Payments", "Company name": "Zeal", "City": "Fremont", "State": "CA", "Posting date": "14.10.2021"}, {"Job title": "Consultant, PCI Payments - Enterprise", "Company name": "Coalfire", "City": "Westminster", "State": "CO", "Posting date": "14.10.2021"}, {"Job title": "Digital Relationship Manager, Foreign Exchange and Payments", "Company name": "Western Union", "City": "Baltimore", "State": "MD, Remote", "Posting date": "29.09.2021"}, {"Job title": "Work From Home Senior Customer Service Expert - eBay Payments Agent", "Company name": "eBay Inc.", "City": "San Antonio", "State": "TX, Remote", "Posting date": "14.10.2021"}, {"Job title": "Enterprise Payments Customer Success Consultant", "Company name": "Allstate", "City": "Northbrook", "State": "IL, Remote", "Posting date": ">18.09.2021"}, {"Job title": "Payments and Credit Solutions Manager", "Company name": "Getaround", "City": "", "State": "Remote", "Posting date": "01.10.2021"}, {"Job title": "Director of Payments", "Company name": "Remote", "City": "", "State": "New York State, Remote", "Posting date": "15.10.2021"}, {"Job title": "Wholesale Payments - CS&I Strategic Program Group - Associate", "Company name": "JPMorgan Chase Bank, N.A.", "City": "Tampa", "State": "FL", "Posting date": "11.10.2021"}]